pgkv/__init__.py
pgkv/pgkv.py
pgkv/utils.py
pgkv-0.2402.0.dist-info/LICENSE
pgkv-0.2402.0.dist-info/METADATA
pgkv-0.2402.0.dist-info/WHEEL
pgkv-0.2402.0.dist-info/top_level.txt
pgkv-0.2402.0.dist-info/RECORD
