Metadata-Version: 2.1
Name: pgkv
Version: 0.2402.0
Summary: Use PostgreSQL as a key-value store
Home-page: https://github.com/labteral/pgkv
Author: Rodrigo Martínez Castaño
Author-email: rodrigo@martinez.gal
License: GNU General Public License v3 (GPLv3)
Classifier: Development Status :: 4 - Beta
Classifier: Environment :: Console
Classifier: Intended Audience :: Developers
Classifier: License :: OSI Approved :: GNU General Public License v3 (GPLv3)
Classifier: Operating System :: POSIX :: Linux
Classifier: Programming Language :: Python :: 3.6
Classifier: Programming Language :: Python :: Implementation :: PyPy
Classifier: Topic :: Software Development :: Libraries :: Python Modules
Requires-Python: >=3.6
License-File: LICENSE
Requires-Dist: psycopg2-binary (<3.0.0,>=2.9.9)
Requires-Dist: psycopg2 (<3.0.0,>=2.9.9)
